lixi/_LIXI.py
lixi/_Message.py
lixi/__init__.py
lixi/_command_line.py
lixi/_customise_schema.py
lixi/_explode_schema.py
lixi/_jsonschema_functions.py
lixi/_path_functions.py
lixi/_schema_documentation.py
lixi/_schematron_functions.py
lixi/_xml_to_json.py
lixi/_xslt_transform.py
lixi/customization.xsd
lixi/documentation/.gitignore
lixi/documentation/.gitlab-ci.yml
lixi/documentation/README.md
lixi/documentation/create_documentation.py
lixi/documentation/index.html
lixi/documentation/search.html
lixi/documentation/css/extra.css
lixi/documentation/css/highlight.css
lixi/documentation/css/theme.css
lixi/documentation/css/theme_extra.css
lixi/documentation/fonts/fontawesome-webfont.eot
lixi/documentation/fonts/fontawesome-webfont.svg
lixi/documentation/fonts/fontawesome-webfont.ttf
lixi/documentation/fonts/fontawesome-webfont.woff
lixi/documentation/img/clip.png
lixi/documentation/img/favicon.ico
lixi/documentation/img/info-icon.png
lixi/documentation/img/info.png
lixi/documentation/img/lixi_logo_100.png
lixi/documentation/img/wheel.gif
lixi/documentation/js/GenerateHTML.js
lixi/documentation/js/LIXI-Master-Schema.js
lixi/documentation/js/LIXI_Glossary.js
lixi/documentation/js/jquery-2.1.1.min.js
lixi/documentation/js/marked.js
lixi/documentation/js/modernizr-2.8.3.min.js
lixi/documentation/js/theme.js
lixi/documentation/js/vkbeautify.0.99.00.beta.js
lixi/documentation/mkdocs/js/lunr.min.js
lixi/documentation/mkdocs/js/mustache.min.js
lixi/documentation/mkdocs/js/require.js
lixi/documentation/mkdocs/js/search.js
lixi/documentation/mkdocs/js/text.js
lixi-0.12.7.dist-info/LICENSE
lixi-0.12.7.dist-info/METADATA
lixi-0.12.7.dist-info/WHEEL
lixi-0.12.7.dist-info/top_level.txt
lixi-0.12.7.dist-info/RECORD
