Metadata-Version: 2.1
Name: lixi
Version: 0.12.7
Summary: lixi is a python package to manipulate a valid LIXI 2 message and schema.
Home-page: https://standards.lixi.org.au/lixi-tech/lixi-pypi
Author: Ammar Khan
Author-email: lixilab@lixi.org.au
License: MIT
Platform: UNKNOWN
Classifier: License :: OSI Approved :: MIT License
Classifier: Programming Language :: Python
Classifier: Programming Language :: Python :: 3
License-File: LICENSE
Requires-Dist: lxml (>=4.4.1)
Requires-Dist: isodate (>=0.6.0)
Requires-Dist: xmljson (>=0.2.0)
Requires-Dist: jsonschema (>=3.0.2)
Requires-Dist: importlib-resources (>=6.4.0)
